aimllabnew/__init__.py
aimllabnew/codes.py
aimllabnew/testing.py
aimllabnew-0.2.3.dist-info/METADATA
aimllabnew-0.2.3.dist-info/WHEEL
aimllabnew-0.2.3.dist-info/top_level.txt
aimllabnew-0.2.3.dist-info/RECORD
